flask_googlemaps/__init__.py
flask_googlemaps/icons.py
flask_googlemaps/templates/googlemaps/gmap.html
flask_googlemaps/templates/googlemaps/gmapjs.html
flask_googlemaps-0.3.0.dist-info/LICENSE
flask_googlemaps-0.3.0.dist-info/WHEEL
flask_googlemaps-0.3.0.dist-info/METADATA
flask_googlemaps-0.3.0.dist-info/RECORD
