Metadata-Version: 2.1
Name: flask-googlemaps
Version: 0.3.0
Summary: Easy way to add GoogleMaps to Flask Applications
Home-page: https://flaskextensions.com
License: MIT
Author: Riverfount - Vulgo Vicente Marçal
Author-email: vicente.marcal@gmail.com
Requires-Python: >=3.6
Classifier: Development Status :: 5 - Production/Stable
Classifier: Environment :: Web Environment
Classifier: Intended Audience :: Developers
Classifier: License :: OSI Approved :: MIT License
Classifier: Operating System :: OS Independent
Classifier: Programming Language :: Python :: 2
Classifier: Programming Language :: Python :: 3
Classifier: Programming Language :: Python :: 3.6
Classifier: Programming Language :: Python :: 3.7
Classifier: Programming Language :: Python :: 3.8
Classifier: Topic :: Internet :: WWW/HTTP :: Dynamic Content
Classifier: Topic :: Software Development :: Libraries :: Python Modules
Requires-Dist: flask (>=0.10)
Project-URL: Repository, https://github.com/flask-extensions/Flask-GoogleMaps
